kushim/__init__.py
kushim/chunking.py
kushim/config.py
kushim/pipeline.py
kushim/qagen.py
kushim/source.py
kushim/validation.py
kushim/utils/__init__.py
kushim/utils/encryption.py
kushim/utils/huggingface.py
kushim/utils/keys.py
kushim/utils/merging.py
kushim/utils/processing.py
kushim-0.0.3.dist-info/METADATA
kushim-0.0.3.dist-info/WHEEL
kushim-0.0.3.dist-info/RECORD
